pollo/requester.py
pollo/server.py
pollo-0.0.1.dist-info/LICENSE
pollo-0.0.1.dist-info/METADATA
pollo-0.0.1.dist-info/WHEEL
pollo-0.0.1.dist-info/top_level.txt
pollo-0.0.1.dist-info/RECORD
